{
  "vibe": "System Offline",
  "weeks": [
    "W-3",
    "W-2",
    "W-1",
    "Current"
  ],
  "volume": {
    "swim": [
      0,
      0,
      0,
      0
    ],
    "bike": [
      0,
      0,
      0,
      0.0
    ],
    "run": [
      0,
      0,
      0,
      0.0
    ],
    "strength": [
      0,
      0,
      0,
      0
    ]
  },
  "compliance": {
    "score": [
      0,
      0,
      0,
      0
    ]
  },
  "engagement": {
    "human": [
      0,
      0,
      0,
      1
    ],
    "ai": [
      0,
      0,
      0,
      0
    ]
  }
}